langchain_google_cloud_sql_mssql/__init__.py
langchain_google_cloud_sql_mssql/chat_message_history.py
langchain_google_cloud_sql_mssql/engine.py
langchain_google_cloud_sql_mssql/loader.py
langchain_google_cloud_sql_mssql/py.typed
langchain_google_cloud_sql_mssql/version.py
langchain_google_cloud_sql_mssql-0.3.0.dist-info/LICENSE
langchain_google_cloud_sql_mssql-0.3.0.dist-info/METADATA
langchain_google_cloud_sql_mssql-0.3.0.dist-info/WHEEL
langchain_google_cloud_sql_mssql-0.3.0.dist-info/top_level.txt
langchain_google_cloud_sql_mssql-0.3.0.dist-info/RECORD
